url_package/SDSBL.py
url_package/__init__.py
url_package/gglsbl/__init__.py
url_package/gglsbl/_version.py
url_package/gglsbl/client.py
url_package/gglsbl/protocol.py
url_package/gglsbl/storage.py
url_package/gglsbl/utils.py
url_package-1.0.0.1.dist-info/DESCRIPTION.rst
url_package-1.0.0.1.dist-info/METADATA
url_package-1.0.0.1.dist-info/RECORD
url_package-1.0.0.1.dist-info/WHEEL
url_package-1.0.0.1.dist-info/metadata.json
url_package-1.0.0.1.dist-info/top_level.txt
